binaryfile/__init__.py
binaryfile/fileformat.py
binaryfile/utils.py
binaryfile-1.2.0.dist-info/LICENSE
binaryfile-1.2.0.dist-info/METADATA
binaryfile-1.2.0.dist-info/WHEEL
binaryfile-1.2.0.dist-info/top_level.txt
binaryfile-1.2.0.dist-info/RECORD
