Metadata-Version: 2.1
Name: binaryfile
Version: 1.2.0
Summary: A library for defining the structure of a binary file and then reading or writing it.
Home-page: https://github.com/Faxmachinen/pybinaryfile/tree/1.2.0
Author: Faxmachinen
Author-email: binaryfile@faxmachinen.com
License: UNKNOWN
Platform: UNKNOWN
Classifier: Programming Language :: Python :: 3
Classifier: License :: OSI Approved :: MIT License
Classifier: Operating System :: OS Independent
Requires-Python: >=3.6
